{
  "updateDate": "2025-09-16T05:41:35.733Z",
  "statistics": {
    "totalBrokers": 147,
    "updatedBrokers": 97,
    "successRate": "65.99%",
    "totalFieldsUpdated": 303
  },
  "fieldsUpdated": {
    "country": 97,
    "website_url": 97,
    "trust_score": 97,
    "logo_url": 2,
    "spread_type": 10
  },
  "errors": [],
  "nextSteps": [
    "1. Verify database updates were successful",
    "2. Run final database analysis to check remaining empty columns",
    "3. Consider additional web scraping for missing information",
    "4. Generate missing SEO content automatically"
  ]
}